maxFstoolkit/__init__.py
maxFstoolkit/pandas/__init__.py
maxFstoolkit/pandas/data_frame.py
maxFstoolkit-0.0.1.dist-info/LICENSE
maxFstoolkit-0.0.1.dist-info/METADATA
maxFstoolkit-0.0.1.dist-info/WHEEL
maxFstoolkit-0.0.1.dist-info/top_level.txt
maxFstoolkit-0.0.1.dist-info/RECORD
